{
  "stage": 4,
  "class": "H60",
  "classId": 1225487,
  "available": true,
  "courseLengthM": 4470,
  "climbM": 150,
  "controls": [
    {
      "idx": 0,
      "code": "S2",
      "type": 0,
      "E": 2552859.62,
      "N": 1115808.83
    },
    {
      "idx": 1,
      "code": "49",
      "type": 1,
      "E": 2552909.2,
      "N": 1116008.21
    },
    {
      "idx": 2,
      "code": "35",
      "type": 1,
      "E": 2553086.96,
      "N": 1116450.5
    },
    {
      "idx": 3,
      "code": "102",
      "type": 1,
      "E": 2553175.87,
      "N": 1116358.21
    },
    {
      "idx": 4,
      "code": "117",
      "type": 1,
      "E": 2553290.89,
      "N": 1116477.83
    },
    {
      "idx": 5,
      "code": "67",
      "type": 1,
      "E": 2553219.78,
      "N": 1116736.29
    },
    {
      "idx": 6,
      "code": "212",
      "type": 1,
      "E": 2553266.74,
      "N": 1116809.3
    },
    {
      "idx": 7,
      "code": "80",
      "type": 1,
      "E": 2553439.06,
      "N": 1116562.4
    },
    {
      "idx": 8,
      "code": "91",
      "type": 1,
      "E": 2553431.17,
      "N": 1116460.51
    },
    {
      "idx": 9,
      "code": "54",
      "type": 1,
      "E": 2553314.2,
      "N": 1116238.3
    },
    {
      "idx": 10,
      "code": "202",
      "type": 1,
      "E": 2553137.17,
      "N": 1116067.03
    },
    {
      "idx": 11,
      "code": "108",
      "type": 1,
      "E": 2553838.51,
      "N": 1115981.7
    },
    {
      "idx": 12,
      "code": "61",
      "type": 1,
      "E": 2554357.57,
      "N": 1116098.71
    },
    {
      "idx": 13,
      "code": "62",
      "type": 1,
      "E": 2554554.02,
      "N": 1115941.03
    },
    {
      "idx": 14,
      "code": "64",
      "type": 1,
      "E": 2554213.3,
      "N": 1115713.04
    },
    {
      "idx": 15,
      "code": "200",
      "type": 1,
      "E": 2554023.29,
      "N": 1115803.53
    },
    {
      "idx": 16,
      "code": "Z1",
      "type": 2,
      "E": 2553976.52,
      "N": 1115725.51
    }
  ],
  "legs": [
    {
      "idx": 0,
      "fromCode": "S2",
      "toCode": "49",
      "distM": 205,
      "upM": 0,
      "downM": 65
    },
    {
      "idx": 1,
      "fromCode": "49",
      "toCode": "35",
      "distM": 477,
      "upM": 25,
      "downM": 55
    },
    {
      "idx": 2,
      "fromCode": "35",
      "toCode": "102",
      "distM": 128,
      "upM": 25,
      "downM": 0
    },
    {
      "idx": 3,
      "fromCode": "102",
      "toCode": "117",
      "distM": 166,
      "upM": 15,
      "downM": 20
    },
    {
      "idx": 4,
      "fromCode": "117",
      "toCode": "67",
      "distM": 268,
      "upM": 25,
      "downM": 25
    },
    {
      "idx": 5,
      "fromCode": "67",
      "toCode": "212",
      "distM": 87,
      "upM": 15,
      "downM": 10
    },
    {
      "idx": 6,
      "fromCode": "212",
      "toCode": "80",
      "distM": 301,
      "upM": 55,
      "downM": 5
    },
    {
      "idx": 7,
      "fromCode": "80",
      "toCode": "91",
      "distM": 102,
      "upM": 5,
      "downM": 10
    },
    {
      "idx": 8,
      "fromCode": "91",
      "toCode": "54",
      "distM": 251,
      "upM": 5,
      "downM": 15
    },
    {
      "idx": 9,
      "fromCode": "54",
      "toCode": "202",
      "distM": 246,
      "upM": 5,
      "downM": 35
    },
    {
      "idx": 10,
      "fromCode": "202",
      "toCode": "108",
      "distM": 707,
      "upM": 30,
      "downM": 55
    },
    {
      "idx": 11,
      "fromCode": "108",
      "toCode": "61",
      "distM": 532,
      "upM": 15,
      "downM": 50
    },
    {
      "idx": 12,
      "fromCode": "61",
      "toCode": "62",
      "distM": 252,
      "upM": 0,
      "downM": 70
    },
    {
      "idx": 13,
      "fromCode": "62",
      "toCode": "64",
      "distM": 410,
      "upM": 15,
      "downM": 40
    },
    {
      "idx": 14,
      "fromCode": "64",
      "toCode": "200",
      "distM": 210,
      "upM": 30,
      "downM": 5
    },
    {
      "idx": 15,
      "fromCode": "200",
      "toCode": "Z1",
      "distM": 91,
      "upM": 0,
      "downM": 5
    }
  ],
  "map": {
    "pngPath": "maps/s4_H60.png",
    "width": 2969,
    "height": 1989,
    "lv95ToPixel": [
      [
        1.12376237981797,
        -0.07070113647322639,
        -2789584.8987971246
      ],
      [
        -0.07070113647322639,
        -1.12376237981797,
        1435994.999507797
      ]
    ]
  }
}