{
  "stage": 6,
  "class": "HE",
  "classId": 1225597,
  "available": true,
  "courseLengthM": 5910,
  "climbM": 340,
  "controls": [
    {
      "idx": 0,
      "code": "S1",
      "type": 0,
      "E": 2555593.73,
      "N": 1123801.92
    },
    {
      "idx": 1,
      "code": "50",
      "type": 1,
      "E": 2555922.2,
      "N": 1123804.96
    },
    {
      "idx": 2,
      "code": "138",
      "type": 1,
      "E": 2555891.59,
      "N": 1123699.57
    },
    {
      "idx": 3,
      "code": "51",
      "type": 1,
      "E": 2556619.51,
      "N": 1123750.88
    },
    {
      "idx": 4,
      "code": "63",
      "type": 1,
      "E": 2556866.61,
      "N": 1123674.07
    },
    {
      "idx": 5,
      "code": "64",
      "type": 1,
      "E": 2556931.74,
      "N": 1123811.12
    },
    {
      "idx": 6,
      "code": "44",
      "type": 1,
      "E": 2556772.99,
      "N": 1123843.27
    },
    {
      "idx": 7,
      "code": "115",
      "type": 1,
      "E": 2556606.27,
      "N": 1124258.57
    },
    {
      "idx": 8,
      "code": "87",
      "type": 1,
      "E": 2556599.8,
      "N": 1124398.91
    },
    {
      "idx": 9,
      "code": "94",
      "type": 1,
      "E": 2556761.78,
      "N": 1124441.99
    },
    {
      "idx": 10,
      "code": "121",
      "type": 1,
      "E": 2557114.84,
      "N": 1124415.79
    },
    {
      "idx": 11,
      "code": "47",
      "type": 1,
      "E": 2557102.24,
      "N": 1124574.19
    },
    {
      "idx": 12,
      "code": "97",
      "type": 1,
      "E": 2556991.95,
      "N": 1124599.76
    },
    {
      "idx": 13,
      "code": "57",
      "type": 1,
      "E": 2557079.87,
      "N": 1124226.05
    },
    {
      "idx": 14,
      "code": "108",
      "type": 1,
      "E": 2556970.27,
      "N": 1124132.23
    },
    {
      "idx": 15,
      "code": "43",
      "type": 1,
      "E": 2556597.1,
      "N": 1123969.37
    },
    {
      "idx": 16,
      "code": "38",
      "type": 1,
      "E": 2556347.87,
      "N": 1124016.42
    },
    {
      "idx": 17,
      "code": "66",
      "type": 1,
      "E": 2556396.83,
      "N": 1124198.16
    },
    {
      "idx": 18,
      "code": "204",
      "type": 1,
      "E": 2556361.06,
      "N": 1124294.24
    },
    {
      "idx": 19,
      "code": "46",
      "type": 1,
      "E": 2555508.79,
      "N": 1124276.34
    },
    {
      "idx": 20,
      "code": "200",
      "type": 1,
      "E": 2555446.16,
      "N": 1124189.65
    },
    {
      "idx": 21,
      "code": "Z1",
      "type": 2,
      "E": 2555292.92,
      "N": 1124120.75
    }
  ],
  "legs": [
    {
      "idx": 0,
      "fromCode": "S1",
      "toCode": "50",
      "distM": 328,
      "upM": 45,
      "downM": 5
    },
    {
      "idx": 1,
      "fromCode": "50",
      "toCode": "138",
      "distM": 110,
      "upM": 15,
      "downM": 0
    },
    {
      "idx": 2,
      "fromCode": "138",
      "toCode": "51",
      "distM": 730,
      "upM": 40,
      "downM": 90
    },
    {
      "idx": 3,
      "fromCode": "51",
      "toCode": "63",
      "distM": 259,
      "upM": 15,
      "downM": 10
    },
    {
      "idx": 4,
      "fromCode": "63",
      "toCode": "64",
      "distM": 152,
      "upM": 0,
      "downM": 50
    },
    {
      "idx": 5,
      "fromCode": "64",
      "toCode": "44",
      "distM": 162,
      "upM": 15,
      "downM": 5
    },
    {
      "idx": 6,
      "fromCode": "44",
      "toCode": "115",
      "distM": 448,
      "upM": 0,
      "downM": 90
    },
    {
      "idx": 7,
      "fromCode": "115",
      "toCode": "87",
      "distM": 140,
      "upM": 0,
      "downM": 25
    },
    {
      "idx": 8,
      "fromCode": "87",
      "toCode": "94",
      "distM": 168,
      "upM": 25,
      "downM": 15
    },
    {
      "idx": 9,
      "fromCode": "94",
      "toCode": "121",
      "distM": 354,
      "upM": 70,
      "downM": 20
    },
    {
      "idx": 10,
      "fromCode": "121",
      "toCode": "47",
      "distM": 159,
      "upM": 0,
      "downM": 15
    },
    {
      "idx": 11,
      "fromCode": "47",
      "toCode": "97",
      "distM": 113,
      "upM": 10,
      "downM": 0
    },
    {
      "idx": 12,
      "fromCode": "97",
      "toCode": "57",
      "distM": 384,
      "upM": 20,
      "downM": 10
    },
    {
      "idx": 13,
      "fromCode": "57",
      "toCode": "108",
      "distM": 144,
      "upM": 15,
      "downM": 10
    },
    {
      "idx": 14,
      "fromCode": "108",
      "toCode": "43",
      "distM": 407,
      "upM": 45,
      "downM": 30
    },
    {
      "idx": 15,
      "fromCode": "43",
      "toCode": "38",
      "distM": 254,
      "upM": 50,
      "downM": 10
    },
    {
      "idx": 16,
      "fromCode": "38",
      "toCode": "66",
      "distM": 188,
      "upM": 0,
      "downM": 25
    },
    {
      "idx": 17,
      "fromCode": "66",
      "toCode": "204",
      "distM": 103,
      "upM": 0,
      "downM": 10
    },
    {
      "idx": 18,
      "fromCode": "204",
      "toCode": "46",
      "distM": 852,
      "upM": 105,
      "downM": 20
    },
    {
      "idx": 19,
      "fromCode": "46",
      "toCode": "200",
      "distM": 107,
      "upM": 0,
      "downM": 20
    },
    {
      "idx": 20,
      "fromCode": "200",
      "toCode": "Z1",
      "distM": 168,
      "upM": 0,
      "downM": 40
    }
  ],
  "map": {
    "pngPath": "maps/s6_HE.png",
    "width": 3046,
    "height": 3580,
    "lv95ToPixel": [
      [
        1.1237623786081194,
        -0.07070113619701554,
        -2791921.20073334
      ],
      [
        -0.07070113619701554,
        -1.1237623786081194,
        1446681.0383788277
      ]
    ]
  }
}